ecdh_x25519-0.1.1.dist-info/METADATA
ecdh_x25519-0.1.1.dist-info/WHEEL
ecdh_x25519/__init__.py
ecdh_x25519/__init__.pyi
ecdh_x25519/ecdh_x25519.cp312-win_amd64.pyd
ecdh_x25519/py.typed
ecdh_x25519-0.1.1.dist-info/RECORD
