Metadata-Version: 2.4
Name: ecdh_x25519
Version: 0.1.1
